spaceone/__init__.py
spaceone/secret/__init__.py
spaceone/secret/api/__init__.py
spaceone/secret/api/v1/__init__.py
spaceone/secret/api/v1/secret.py
spaceone/secret/api/v1/secret_group.py
spaceone/secret/api/v1/trusted_secret.py
spaceone/secret/conf/__init__.py
spaceone/secret/conf/global_conf.py
spaceone/secret/conf/proto_conf.py
spaceone/secret/connector/__init__.py
spaceone/secret/connector/aws_secret_manager_connector.py
spaceone/secret/connector/consul_connector.py
spaceone/secret/connector/etcd_connector.py
spaceone/secret/connector/identity_connector.py
spaceone/secret/connector/mongodb_connector.py
spaceone/secret/connector/vault_connector.py
spaceone/secret/error/__init__.py
spaceone/secret/error/custom.py
spaceone/secret/handler/__init__.py
spaceone/secret/handler/encrypt_mutation_handler.py
spaceone/secret/info/__init__.py
spaceone/secret/info/common_info.py
spaceone/secret/info/secret_group_info.py
spaceone/secret/info/secret_info.py
spaceone/secret/info/trusted_secret_info.py
spaceone/secret/lib/__init__.py
spaceone/secret/manager/__init__.py
spaceone/secret/manager/identity_manager.py
spaceone/secret/manager/secret_connector_manager.py
spaceone/secret/manager/secret_group_manager.py
spaceone/secret/manager/secret_manager.py
spaceone/secret/manager/trusted_secret_manager.py
spaceone/secret/model/__init__.py
spaceone/secret/model/secret_group_model.py
spaceone/secret/model/secret_model.py
spaceone/secret/model/trusted_secret_model.py
spaceone/secret/service/__init__.py
spaceone/secret/service/secret_group_service.py
spaceone/secret/service/secret_service.py
spaceone/secret/service/trusted_secret_service.py
spaceone_secret-1.12.0.dist-info/METADATA
spaceone_secret-1.12.0.dist-info/WHEEL
spaceone_secret-1.12.0.dist-info/top_level.txt
spaceone_secret-1.12.0.dist-info/RECORD
