Metadata-Version: 2.1
Name: spaceone-secret
Version: 1.12.0
Summary: SpaceONE secret service
Home-page: https://www.spaceone.dev/
Author: MEGAZONE SpaceONE Team
Author-email: admin@spaceone.dev
License: Apache License 2.0
Platform: UNKNOWN
Requires-Dist: spaceone-core
Requires-Dist: spaceone-api
Requires-Dist: mongoengine
Requires-Dist: mongomock
Requires-Dist: redis
Requires-Dist: boto3
Requires-Dist: hvac
Requires-Dist: python-consul
